geobuf/__init__.py
geobuf/decode.py
geobuf/encode.py
geobuf/geobuf_pb2.py
geobuf/scripts/__init__.py
geobuf/scripts/cli.py
geobuf-1.1.1.dist-info/DESCRIPTION.rst
geobuf-1.1.1.dist-info/METADATA
geobuf-1.1.1.dist-info/RECORD
geobuf-1.1.1.dist-info/WHEEL
geobuf-1.1.1.dist-info/entry_points.txt
geobuf-1.1.1.dist-info/metadata.json
geobuf-1.1.1.dist-info/top_level.txt
