Metadata-Version: 1.0
Name: geobuf
Version: 1.1.1
Summary: Geobuf is a compact binary geospatial format for lossless compression of GeoJSON and TopoJSON data.
Home-page: https://github.com/mapbox/pygeobuf
Author: Vladimir Agafonkin
Author-email: vladimir@mapbox.com
License: MIT
Keywords: data gis geojson topojson protobuf
Platform: UNKNOWN
